risk_normalization/__init__.py
risk_normalization/risk_normalization.py
risk_normalization-1.1.2.dist-info/LICENSE.md
risk_normalization-1.1.2.dist-info/METADATA
risk_normalization-1.1.2.dist-info/WHEEL
risk_normalization-1.1.2.dist-info/top_level.txt
risk_normalization-1.1.2.dist-info/RECORD
