Metadata-Version: 2.1
Name: risk-normalization
Version: 1.1.2
Summary: Compute safe_f and CAR25 for a list of trades
Home-page: https://github.com/howardbandy/risk_normalization/blob/master/risk_normalization.py
Author: Dr. Howard Bandy
Author-email: howard@blueowlpress.com
License: MIT
Platform: UNKNOWN
Requires-Python: >=3.6
